{
	"backgrounds": [
		"Park",
		"OutdoorsSeaside",
		"HallwayClassroom"
	],
	"characters": [
		"TeacherWim",
		"TeacherInge"
	],
	"departments": [
		{
			"label": "All",
			"type": "ALL",
			"racks": [
			]
		},
		{
			"label": "Shared",
			"type": "SHARED",
			"racks": [
				{
					"maxWidthInTiles": 5,
					"items": [
					]
				}
			]
		},
		{
			"label": "Common",
			"type": "COMMON",
			"racks": [
				{
					"maxWidthInTiles": 4,
					"items": [
						"level-sign_3x4",
						"finish_1x10"
					]
				},
				{
					"maxWidthInTiles": 8,
					"items": [
						"soil-surface_8x1",
						"meadow-surface_8x1",
						"stone-surface_8x1",
						"lava-surface_8x1",
						"snow-surface_8x1",
						"ice-surface_8x1",
						"sea_8x1",
						"rapid-river_4x1"
					]
				},
				{
					"maxWidthInTiles": 4,
					"items": [
						"tiled-floor_8x1",
						"soil_15x1",
						"soil_4x1"
					]
				},
				{
					"maxWidthInTiles": 4,
					"items": [
						"stone_4x1",
						"stone_1x1"
					]
				},
				{
					"maxWidthInTiles": 8,
					"items": [
						"ATMOS_dusk_8",
						"ATMOS_night_8",
						"ATMOS_wind_8",
						"ATMOS_blast_8",
						"ATMOS_rain_15",
						"ATMOS_heavyrain_15",
						"ATMOS_snowfall_15",
						"ATMOS_blizzard_15"
					]
				},
				{
					"maxWidthInTiles": 10,
					"items": [
						"teleport-entrance-2",
						"teleport-entrance-5",
						"teleport-entrance-10",
						"teleport-entrance-20",
						"teleport-entrance-50"
					]
				}
			]
		},
		{
			"label": "Wood",
			"type": "EXTENSION",
			"racks": [
				{
					"maxWidthInTiles": 4,
					"items": [
						"plank_4x1",
						"plank-birds_4x2"
					]
				},
				{
					"maxWidthInTiles": 2,
					"items": [
						"chest_2x2",
						"barrel_2x2"
					]
				},
				{
					"maxWidthInTiles": 18,
					"items": [
						"wood-pillar_1x3",
						"wood-log-trunk_12x2",
						"wood-log-trunk_6x2",
						"wood-log-platform_6x5",
						"wood-log-platform-cut_6x6",
						"wood-log-cut_12x4",
						"wood-trunk-chopped_2x1"
					]
				},
				{
					"maxWidthInTiles": 3,
					"items": [
						"dynamite-box_3x2",
						"fireworks-box_3x2"
					]
				}
			]
		},
		{
			"label": "Enemies",
			"type": "EXTENSION",
			"racks": [
				{
					"maxWidthInTiles": 8,
					"items": [
						"snowy-owl_3x3",
						"snowy-owl_2x2",
						"seagull_2x2",
						"albatros-3x2"
					]
				},
				{
					"maxWidthInTiles": 6,
					"items": [
						"cactus_2x3",
						"snake_2x2",
						"halloween-pumpkin_2x2",
						"frog-sit_1x1",
						"frog-jump_1x1"
					]
				},
				{
					"maxWidthInTiles": 12,
					"items": [
						"bomb_1x1",
						"firecracker-blue_2x2",
						"firecracker-red_1x2"
					]
				},
				{
					"maxWidthInTiles": 16,
					"items": [
						"shark_3x4",
						"narwhal_9x3",
						"polar-bear_7x4",
						"wolf_5x3"
					]
				},
				{
					"maxWidthInTiles": 12,
					"items": [
						"snowman-throwing_5x5",
						"grinch_4x6"
					]
				},
				{
					"maxWidthInTiles": 5,
					"items": [
						"snowball-rolling_2x2",
						"snowball-rolling_3x3"
					]
				}
			]
		},
		{
			"label": "Rewards",
			"type": "EXTENSION",
			"racks": [
				{
					"maxWidthInTiles": 5,
					"items": [
						"medal-gold_1x2",
						"gift_2x2",
						"unicorn-emblem_2x2",
						"coin_1x1"
					]
				},
				{
					"maxWidthInTiles": 5,
					"items": [
						"treasure-chest_5x4"
					]
				}
			]
		},
		{
			"label": "Effects",
			"type": "EXTENSION",
			"racks": [
				{
					"maxWidthInTiles": 1,
					"items": [
						"elixir-green_1x1"
					]
				},
				{
					"maxWidthInTiles": 1,
					"items": [
						"elixir-yellow_1x1"
					]
				},
				{
					"maxWidthInTiles": 1,
					"items": [
						"elixir-purple_1x1"
					]
				}
			]
		},
		{
			"label": "Scenery",
			"type": "EXTENSION",
			"racks": [
				{
					"maxWidthInTiles": 3,
					"items": [
						"cloud_3x2",
						"cloud-dark_3x2"
					]
				},
				{
					"maxWidthInTiles": 8,
					"items": [
						"horse-white_7x6",
						"horse-brown_4x5"
					]
				},
				{
					"maxWidthInTiles": 4,
					"items": [
						"dwarf-wobbling_1x2"
					]
				}
			]
		},
		{
			"label": "School",
			"type": "EXTENSION",
			"racks": [
				{
					"maxWidthInTiles": 8,
					"items": [
						"desk-bright_4x2",
						"desk-dark_4x2",
						"desk-school_4x2",
						"book-stack_2x2"
					]
				},
				{
					"maxWidthInTiles": 4,
					"items": [
						"book-stack_3x8"
					]
				},
				{
					"maxWidthInTiles": 4,
					"items": [
						"guitar_2x2",
						"medal-gold_1x2"
					]
				},
				{
					"maxWidthInTiles": 2,
					"items": [
						"score-perfect_2x2",
						"score-nill_2x2"
					]
				},
				{
					"maxWidthInTiles": 12,
					"items": [
						"angry-teacher_4x4",
						"bully-boy_5x5",
						"bully-boy_2x2"
					]
				},
				{
					"maxWidthInTiles": 4,
					"items": [
						"ovsg-papers_3x4"
					]
				}
			]
		}
	]
}
